<?xml version="1.0" encoding="UTF-8" standalone="yes"?>
<ns3:mods xsi:schemaLocation="http://www.loc.gov/mods/v3 http://www.loc.gov/standards/mods/v3/mods-3-2.xsd" xmlns:xsi="http://www.w3.org/2001/XMLSchema-instance" xmlns:ns3="http://www.loc.gov/mods/v3" xmlns:ns2="http://www.w3.org/1999/xlink">
    <ns3:titleInfo>
        <ns3:title>Alba, Fernando Alvarez de Toledo, duque de,</ns3:title>
    </ns3:titleInfo>
    <ns3:language>
        <ns3:languageTerm type="code" authority="iso639-2b">eng</ns3:languageTerm>
        <ns3:languageTerm type="text">eng</ns3:languageTerm>
    </ns3:language>
    <ns3:typeOfResource>still image</ns3:typeOfResource>
    <ns3:originInfo>
        <ns3:dateCreated>1508-1582</ns3:dateCreated>
        <ns3:dateCreated point="start">1508</ns3:dateCreated>
        <ns3:dateCreated point="end">1582</ns3:dateCreated>
    </ns3:originInfo>
    <ns3:subject>
        <ns3:name type="personal" authority="lcnaf">
            <ns3:role>
                <ns3:roleTerm type="text" authority="marcrelator">Depicted</ns3:roleTerm>
                <ns3:roleTerm type="code" authority="marcrelator">dpc</ns3:roleTerm>
            </ns3:role>
            <ns3:namePart type="family">Alba</ns3:namePart>
            <ns3:namePart type="given">Fernando Alvarez de Tole</ns3:namePart>
            <ns3:namePart type="termsOfAddress">duque de</ns3:namePart>
            <ns3:namePart type="date">1507-1582</ns3:namePart>
            <ns3:displayForm>Alba, Fernando Alvarez de Tole, duque de, 1507-1582</ns3:displayForm>
        </ns3:name>
    </ns3:subject>
    <ns3:subject authority="ingest">
        <ns3:topic>Military officer, Spanish.</ns3:topic>
    </ns3:subject>
    <ns3:physicalDescription>
        <ns3:note displayLabel="Kolb Collection Identifier">0013</ns3:note>
    </ns3:physicalDescription>
    <ns3:abstract displayLabel="Scope and Contents note">Ferdinand Alvarez Herzog von Alba geb. 15O8; gest. zu Lissabon 1582. Entsprossen aus einem mit K~nigen verwandten Geschlechte ruhmgekr5nter Feldherr Karls des V. in den ZUgen in Italien, Afrika Ungarn und Deutschland, Statthalter Philipps II. in den Niederlanden:von 1567 bis l573;als Greisnoch im Jahre 1580 Eroberer von Portugal fur seinen Konig Philipp 11. Das Original ist in der K.K.Ambraser Samlung. zu Wie</ns3:abstract>
    <ns3:identifier displayLabel="Image-Master">//</ns3:identifier>
</ns3:mods>
